[
	{
		"name": "Order A",
		"dropOffLocation": {
			"latitude": -1.3178389,
			"longitude": 36.8425681
		},
		"pickUpLocation": {
			"latitude": -1.2833,
			"longitude": 36.8167
		}
	},
	{
		"name": "Order B",
		"dropOffLocation": {
			"latitude": -1.3283943,
			"longitude": 36.8679232
		},
		"pickUpLocation": {
			"latitude": -1.2833,
			"longitude": 36.8167
		}
	},
	{
		"name": "Order C",
		"dropOffLocation": {
			"latitude": -1.3283943,
			"longitude": 36.8679232
		},
		"pickUpLocation": {
			"latitude": -1.3178389,
			"longitude": 36.8425681
		}
	}
]